devqubit_pennylane/__init__.py
devqubit_pennylane/adapter.py
devqubit_pennylane/circuits.py
devqubit_pennylane/py.typed
devqubit_pennylane/results.py
devqubit_pennylane/serialization.py
devqubit_pennylane/snapshot.py
devqubit_pennylane/utils.py
devqubit_pennylane-0.1.10.dist-info/METADATA
devqubit_pennylane-0.1.10.dist-info/WHEEL
devqubit_pennylane-0.1.10.dist-info/entry_points.txt
devqubit_pennylane-0.1.10.dist-info/licenses/LICENSE
devqubit_pennylane-0.1.10.dist-info/RECORD
