Metadata-Version: 2.4
Name: devqubit-pennylane
Version: 0.1.10
Summary: devqubit adapter for Pennylane
Author: devqubit
License-Expression: Apache-2.0
License-File: LICENSE
Keywords: experiment-tracking,pennylane,quantum
Classifier: Development Status :: 3 - Alpha
Classifier: License :: OSI Approved :: Apache Software License
Classifier: Operating System :: OS Independent
Classifier: Programming Language :: Python :: 3
Classifier: Programming Language :: Python :: 3 :: Only
Classifier: Programming Language :: Python :: 3.11
Classifier: Programming Language :: Python :: 3.12
Classifier: Programming Language :: Python :: 3.13
Requires-Python: <3.14,>=3.11
Requires-Dist: devqubit-engine<0.2.0,>=0.1.10
Requires-Dist: pennylane<0.44,>=0.43
